<?xml version="1.0" encoding="iso-8859-1"?>
<Document>
  <Treaty>
    <Template>mtdsg</Template>
    <Header>
      <Chapter>
        <Header>CHAPTER XXVII</Header>
        <Name>ENVIRONMENT</Name>
      </Chapter>
      <ExternalData>
        <Numsect>7</Numsect>
        <Subnumsect>b</Subnumsect>
        <Subtitlesect>Amendment to Annex B of the Kyoto Protocol to the United Nations Framework Convention on Climate Change</Subtitlesect>
        <Conclusion>Nairobi, 17 November 2006</Conclusion>
        <EIF>
          <Label>Not yet in force</Label>
          <Labeltext>see paragraphs (4) and (5) of article 20 of the Protocol which read as follows: "The Amendment to Annex B of the Protocol, shall enter into force for those Parties having accepted it on the ninetieth day after the date of receipt by the Depositary of an instrument of acceptance by at least three fourths of the Parties to this Protocol. The Amendment shall enter into force for any other Party on the ninetieth day after the date on which that Party deposits with the Depositary its instrument of acceptance of the said Amendment.".</Labeltext>
        </EIF>
        <Registration />
        <Status>
          <Label>Status</Label>
          <PartiesLabel>Parties</PartiesLabel>
          <Parties>30</Parties>
        </Status>
        <TreatyText>
          <Label>Text</Label>
          <Text>Doc. &lt;a href="/doc/source/docs/Decision 10_CMP_2-E.pdf" target="_blank"&gt;Decision 10/CMP/2&lt;/a&gt;.</Text>
        </TreatyText>
        <TreatyNote>
          <Text>At the second session of the Conference of the Parties to the Kyoto Protocol, held in Nairobi, Kenya from 6 to 17 November 2006, the Parties adopted an Amendment to Annex B to the Protocol by Decision 10/CMP/2, in accordance with Articles 20 and 21 of the Protocol.</Text>
        </TreatyNote>
      </ExternalData>
    </Header>
    <Participants>
      <Table colsep="0" frame="none" rowsep="0">
        <TGroup cols="2">
          <Thead>
            <Row rowsep="0">
              <Entry colname="1">Participant</Entry>
              <Entry colname="2">Acceptance(A)</Entry>
            </Row>
          </Thead>
          <Tbody>
            <Rows>
              <Row>
                <Entry>Armenia</Entry>
                <Entry>19 Nov 2008 A</Entry>
              </Row>
              <Row>
                <Entry>Australia</Entry>
                <Entry>12 Dec 2007 A</Entry>
              </Row>
              <Row>
                <Entry>Azerbaijan</Entry>
                <Entry>28 Jan 2009 A</Entry>
              </Row>
              <Row>
                <Entry>Belarus</Entry>
                <Entry>6 Jun 2007 A</Entry>
              </Row>
              <Row>
                <Entry>China</Entry>
                <Entry>16 Jul 2010 A</Entry>
              </Row>
              <Row>
                <Entry>Cuba</Entry>
                <Entry>1 Sep 2011 A</Entry>
              </Row>
              <Row>
                <Entry>Czech Republic</Entry>
                <Entry>18 Apr 2007 A</Entry>
              </Row>
              <Row>
                <Entry>Egypt</Entry>
                <Entry>9 Apr 2010 A</Entry>
              </Row>
              <Row>
                <Entry>France</Entry>
                <Entry>[19 Aug 2009 A]</Entry>
              </Row>
              <Row>
                <Entry>Georgia</Entry>
                <Entry>8 Apr 2011 A</Entry>
              </Row>
              <Row>
                <Entry>India</Entry>
                <Entry>18 Nov 2008 A</Entry>
              </Row>
              <Row>
                <Entry>Iran (Islamic Republic of)</Entry>
                <Entry>10 Apr 2012 A</Entry>
              </Row>
              <Row>
                <Entry>Israel</Entry>
                <Entry>28 Dec 2009 A</Entry>
              </Row>
              <Row>
                <Entry>Kazakhstan</Entry>
                <Entry>7 Oct 2011 A</Entry>
              </Row>
              <Row>
                <Entry>Kyrgyzstan</Entry>
                <Entry>2 Nov 2009 A</Entry>
              </Row>
              <Row>
                <Entry>Mauritius</Entry>
                <Entry>23 Sep 2009 A</Entry>
              </Row>
              <Row>
                <Entry>Mexico</Entry>
                <Entry>3 Apr 2009 A</Entry>
              </Row>
              <Row>
                <Entry>Morocco</Entry>
                <Entry>3 Mar 2010 A</Entry>
              </Row>
              <Row>
                <Entry>Norway</Entry>
                <Entry>26 Aug 2008 A</Entry>
              </Row>
              <Row>
                <Entry>Peru</Entry>
                <Entry>25 Jan 2012 A</Entry>
              </Row>
              <Row>
                <Entry>Republic of Korea</Entry>
                <Entry>10 Dec 2009 A</Entry>
              </Row>
              <Row>
                <Entry>Republic of Moldova</Entry>
                <Entry>18 Nov 2008 A</Entry>
              </Row>
              <Row>
                <Entry>Russian Federation</Entry>
                <Entry>27 Jun 2008 A</Entry>
              </Row>
              <Row>
                <Entry>Serbia</Entry>
                <Entry>31 Jul 2009 A</Entry>
              </Row>
              <Row>
                <Entry>South Africa</Entry>
                <Entry>21 Feb 2014 A</Entry>
              </Row>
              <Row>
                <Entry>Syrian Arab Republic</Entry>
                <Entry>16 Jun 2009 A</Entry>
              </Row>
              <Row>
                <Entry>Turkey</Entry>
                <Entry>12 Oct 2017 A</Entry>
              </Row>
              <Row>
                <Entry>Turkmenistan</Entry>
                <Entry>21 Aug 2008 A</Entry>
              </Row>
              <Row>
                <Entry>Ukraine</Entry>
                <Entry>5 Jan 2010 A</Entry>
              </Row>
              <Row>
                <Entry>Uzbekistan</Entry>
                <Entry>16 Oct 2007 A</Entry>
              </Row>
              <Row>
                <Entry>Viet Nam</Entry>
                <Entry>29 Jul 2008 A</Entry>
              </Row>
            </Rows>
          </Tbody>
        </TGroup>
      </Table>
    </Participants>
    <SpecialTables />
    <Declarations />
    <Objections />
    <DeclarationsUnderArticle />
    <Notifications />
    <TerritorialApplications show="YES" />
    <EndNotes />
    <Footer>XXVII 7 b. Environment</Footer>
  </Treaty>
</Document>
